pkgbox/__init__.py
pkgbox/charts.py
pkgbox/date_fn.py
pkgbox/fn.py
pkgbox/islack.py
pkgbox/memton.py
pkgbox/num_fn.py
pkgbox-0.9.18.dist-info/LICENSE
pkgbox-0.9.18.dist-info/METADATA
pkgbox-0.9.18.dist-info/WHEEL
pkgbox-0.9.18.dist-info/top_level.txt
pkgbox-0.9.18.dist-info/RECORD
