Metadata-Version: 2.1
Name: pkgbox
Version: 0.9.18
Summary: Frequently Used Packages for Analytics
Author: alex
Author-email: alex.mathew2k@gmail.com
Keywords: pip,pkgbox
License-File: LICENSE
Requires-Dist: numpy ==1.21.6
Requires-Dist: pandas
Requires-Dist: matplotlib ==3.8.4
Requires-Dist: seaborn
Requires-Dist: scikit-learn
Requires-Dist: typing
Requires-Dist: openpyxl ==3.1.2
Requires-Dist: papermill
Requires-Dist: ipywidgets
Requires-Dist: six
Requires-Dist: tabulate
Requires-Dist: oauth2client
Requires-Dist: polars
Requires-Dist: pandasql
Requires-Dist: nteract-scrapbook
Requires-Dist: networkx
Requires-Dist: duckdb >=0.8.0
Requires-Dist: polars[pyarrow] >=0.18.0
Requires-Dist: adbc-driver-postgresql
Requires-Dist: adbc-driver-manager
Requires-Dist: pyarrow
Requires-Dist: pyzipper
Requires-Dist: typing ; python_version < "3.5"
